{
    "version": "2.27",
    "description": "Allows to download encrypted wiiu files from nintendo's official servers ",
    "homepage": "https://github.com/Xpl0itU/WiiUDownloader",
    "license": "GPL-3.0",
    "url": "https://github.com/Xpl0itU/WiiUDownloader/releases/download/v2.27/WiiUDownloader-Windows.zip",
    "hash": "aab10117088ca262697f628080004ec3bc463541f58b76f3e8125eb9ccf12cf6",
    "bin": "WiiUDownloader.exe",
    "shortcuts": [
        [
            "WiiUDownloader.exe",
            "WiiUDownloader+"
        ]
    ],
    "persist": "settings.json",
    "checkver": "github",
    "autoupdate": {
        "url": "https://github.com/Xpl0itU/WiiUDownloader/releases/download/v$version/WiiUDownloader-Windows.zip"
    }
}
